edlio/__init__.py
edlio/collection.py
edlio/dataset.py
edlio/group.py
edlio/unit.py
edlio/utils.py
edlio/dataio/__init__.py
edlio/dataio/csvdata.py
edlio/dataio/intan.py
edlio/dataio/jsondata.py
edlio/dataio/tsyncfile.py
edlio/dataio/video.py
edlio-0.2.1.dist-info/LICENSE
edlio-0.2.1.dist-info/WHEEL
edlio-0.2.1.dist-info/METADATA
edlio-0.2.1.dist-info/RECORD
