Metadata-Version: 2.1
Name: edlio
Version: 0.2.1
Summary: Module to work with data in an Experiment Directory Layout (EDL) structure
Author: Matthias Klumpp
Requires-Python: >=3.10
Classifier: License :: OSI Approved :: GNU Lesser General Public License v3 or later (LGPLv3+)
Classifier: Intended Audience :: Science/Research
Classifier: Intended Audience :: Developers
Requires-Dist: tomlkit>=0.6.0
Requires-Dist: numpy>=1.17
Requires-Dist: xxhash>=2.0
Requires-Dist: Pint>=0.10
Requires-Dist: pandas ; extra == "test"
Requires-Dist: zstandard ; extra == "test"
Project-URL: Documentation, https://edl.readthedocs.io/
Project-URL: Source, https://github.com/bothlab/edlio
Provides-Extra: test
